flask_reveal/__init__.py
flask_reveal/app.py
flask_reveal/config.py
flask_reveal/blueprints/__init__.py
flask_reveal/blueprints/reveal.py
flask_reveal/templates/presentation.html
flask_reveal/tools/__init__.py
flask_reveal/tools/cli.py
flask_reveal/tools/helpers.py
flask_reveal/tools/commands/__init__.py
flask_reveal/tools/commands/installreveal.py
flask_reveal/tools/commands/mkpresentation.py
flask_reveal/tools/commands/start.py
flask_reveal-0.4.4.dist-info/DESCRIPTION.rst
flask_reveal-0.4.4.dist-info/METADATA
flask_reveal-0.4.4.dist-info/RECORD
flask_reveal-0.4.4.dist-info/WHEEL
flask_reveal-0.4.4.dist-info/entry_points.txt
flask_reveal-0.4.4.dist-info/metadata.json
flask_reveal-0.4.4.dist-info/top_level.txt
tests/__init__.py
tests/test_base.py
tests/test_blueprints.py
tests/test_cli.py
tests/test_helpers.py
