Metadata-Version: 2.0
Name: flask-reveal
Version: 0.4.4
Summary: Make reveal.js presentations with Flask
Home-page: https://github.com/humrochagf/flask-reveal
Author: Humberto Rocha
Author-email: humrochagf@gmail.com
License: MIT
Keywords: flask,reveal.js,presentation
Platform: any
Classifier: Environment :: Console
Classifier: Environment :: Web Environment
Classifier: Framework :: Flask
Classifier: Intended Audience :: Developers
Classifier: License :: OSI Approved :: MIT License
Classifier: Natural Language :: English
Classifier: Programming Language :: Python :: 2
Classifier: Programming Language :: Python :: 2.7
Classifier: Programming Language :: Python :: 3.3
Classifier: Programming Language :: Python :: 3
Classifier: Programming Language :: Python :: 3.4
Classifier: Programming Language :: Python :: 3.5
Classifier: Topic :: Multimedia :: Graphics :: Presentation
Classifier: Topic :: Text Processing :: Markup :: HTML
Requires-Dist: Flask (>=0.12)
